ironic_image_factory/__init__.py
ironic_image_factory/images.py
ironic_image_factory-0.1.1.dist-info/LICENSE
ironic_image_factory-0.1.1.dist-info/METADATA
ironic_image_factory-0.1.1.dist-info/WHEEL
ironic_image_factory-0.1.1.dist-info/entry_points.txt
ironic_image_factory-0.1.1.dist-info/top_level.txt
ironic_image_factory-0.1.1.dist-info/RECORD
