Metadata-Version: 2.1
Name: ironic-image-factory
Version: 0.1.1
Summary: Updates/Adds Glance Images
Home-page: https://github.com/cjloader/ironic-image-factory
Author: cam loader
Author-email: cam.loader@rackspace.com
License: UNKNOWN
Keywords: ironic image factory
Platform: UNKNOWN
Classifier: Development Status :: 3 - Alpha
Classifier: Programming Language :: Python :: 3
Requires-Python: >=3.5
Requires-Dist: python-glanceclient
Requires-Dist: python-ironic-inspector-client
Requires-Dist: python-ironicclient
Requires-Dist: python-keystoneclient
Requires-Dist: python-novaclient
Requires-Dist: urllib3
Requires-Dist: wget
